share_common/__init__.py
share_common/admin.py
share_common/apps.py
share_common/models.py
share_common/settings.py
share_common/tests.py
share_common/views.py
share_common/configurations/__init__.py
share_common/configurations/plugins.py
share_common/configurations/rest_framework.py
share_common/migrations/__init__.py
share_common/utils/__init__.py
share_common/utils/pagination.py
redk_share_common-2.0.0.dist-info/METADATA
redk_share_common-2.0.0.dist-info/WHEEL
redk_share_common-2.0.0.dist-info/top_level.txt
redk_share_common-2.0.0.dist-info/RECORD
