Metadata-Version: 2.1
Name: redk-share-common
Version: 2.0.0
Requires-Dist: django
Requires-Dist: djangorestframework
